{
  "products":
  [
    {
      "id": "VM-22-0001",
      "marketplace": "Bol.com",
      "product": "8720254257709",
      "productId": "9300000015393101",
      "productTitle": "SmartphoneClip® Jeans zwart Bandje geschikt voor Fitbit Versa 3 en Fitbit Sense",
      "keywords": ["fitbit bandje", "fitbit versa 3 bandje", "fitbit versa bandje", "fitbit sense bandje", "fitbit bandje versa 3"],
      "keywordLink":
      [
        "https://www.bol.com/nl/nl/s/?page=1&searchtext=fitbit+bandje&view=list&filter_N=4278199321&12194=11-12&rating=all",
        "https://www.bol.com/nl/nl/s/?page=1&searchtext=fitbit+versa+3+bandje&view=list&filter_N=4278199321&rating=all",
        "https://www.bol.com/nl/nl/s/?page=1&searchtext=fitbit+versa+bandje&view=list&filter_N=4278199321&rating=all",
        "https://www.bol.com/nl/nl/s/?page=1&searchtext=fitbit+sense+bandje&view=list&filter_N=4278199321&rating=all",
        "https://www.bol.com/nl/nl/s/?page=1&searchtext=fitbit+bandje+versa+3&view=list&filter_N=4278199321&rating=all"
      ],
      "isRunning" : false,
      "isMostWantedList": true
    },
    {
      "id": "VM-22-0002",
      "marketplace": "Bol.com",
      "product": "8720618313911",
      "productId": "9300000111074294",
      "productTitle": "SmartphoneClip® Nylon Donkerblauw Bandje geschikt voor Fitbit Versa 3 en Fitbit Sense",
      "keywords": ["fitbit bandje", "fitbit versa 3 bandje", "fitbit versa bandje", "fitbit sense bandje", "fitbit bandje versa 3"],
      "keywordLink":
      [
        "https://www.bol.com/nl/nl/s/?page=1&searchtext=fitbit+bandje&view=list&filter_N=4278199321&12194=11-12&rating=all",
        "https://www.bol.com/nl/nl/s/?page=1&searchtext=fitbit+versa+3+bandje&view=list&filter_N=4278199321&rating=all",
        "https://www.bol.com/nl/nl/s/?page=1&searchtext=fitbit+versa+bandje&view=list&filter_N=4278199321&rating=all",
        "https://www.bol.com/nl/nl/s/?page=1&searchtext=fitbit+sense+bandje&view=list&filter_N=4278199321&rating=all",
        "https://www.bol.com/nl/nl/s/?page=1&searchtext=fitbit+bandje+versa+3&view=list&filter_N=4278199321&rating=all"
      ],
      "isRunning" : false,
      "isMostWantedList": true
    },
    {
      "id": "VM-22-0003",
      "marketplace": "Bol.com",
      "product": "8719325643206",
      "productId": "9200000114663775",
      "productTitle": "SmartphoneClip® Metaal schakel Bandje Dots Roségoud geschikt voor Fitbit Versa (Versa 2, Versa Lite)",
      "keywords": ["fitbit bandje", "fitbit versa bandje", "fitbit bandje versa 2", "fitbit bandje versa"],
      "keywordLink":
      [
        "https://www.bol.com/nl/nl/s/?page=1&searchtext=fitbit+bandje&view=list&filter_N=4278199321&12194=17-18&rating=all",
        "https://www.bol.com/nl/nl/s/?page=1&searchtext=fitbit+versa+bandje&view=list&filter_N=4278199321&rating=all",
        "https://www.bol.com/nl/nl/s/?page=1&searchtext=fitbit+bandje+versa+2&view=list&filter_N=4278199321&rating=all",
        "https://www.bol.com/nl/nl/s/?page=1&searchtext=fitbit+bandje+versa&view=list&filter_N=4278199321&rating=all"
      ],
      "isRunning" : false,
      "isMostWantedList": true
    },
    {
      "id": "VM-22-0004",
      "marketplace": "Bol.com",
      "product": "8719325732672",
      "productId": "9300000002949820",
      "productTitle": "SmartphoneClip® Metaal Scales schakel zwart bandje geschikt voor Fitbit Charge 3 / Charge 4",
      "keywords": ["fitbit bandje", "fitbit bandje charge 3", "fitbit charge 3 bandje", "fitbit bandje charge 4", "fitbit charge 4 bandje"],
      "keywordLink":
      [
        "https://www.bol.com/nl/nl/s/?page=1&searchtext=fitbit+bandje&view=list&filter_N=4278199321&rating=all",
        "https://www.bol.com/nl/nl/s/?page=1&searchtext=fitbit+bandje+charge+3&view=list&filter_N=4278199321&rating=all",
        "https://www.bol.com/nl/nl/s/?page=1&searchtext=fitbit+charge+3+bandje&view=list&filter_N=4278199321&rating=all",
        "https://www.bol.com/nl/nl/s/?page=1&searchtext=fitbit+bandje+charge+4&view=list&filter_N=4278199321&rating=all",
        "https://www.bol.com/nl/nl/s/?page=1&searchtext=fitbit+charge+4+bandje&view=list&filter_N=4278199321&rating=all"
      ],
      "isRunning" : false,
      "isMostWantedList": true
    },
    {
      "id": "VM-22-0005",
      "marketplace": "Bol.com",
      "product": "8719992528301",
      "productId": "9200000108670986",
      "productTitle": "SmartphoneClip® Milanees Bandje Zilver geschikt voor Fitbit Inspire (HR, 2)",
      "keywords": ["fitbit bandje inspire", "fitbit inspire 2 bandje", "fitbit bandje"],
      "keywordLink":
      [
        "https://www.bol.com/nl/nl/s/?page=1&searchtext=fitbit+bandje+inspire&view=list&filter_N=4278199321&rating=all",
        "https://www.bol.com/nl/nl/s/?page=1&searchtext=fitbit+inspire+2+bandje&view=list&filter_N=4278199321&rating=all",
        "https://www.bol.com/nl/nl/s/?page=1&searchtext=fitbit+bandje&view=list&filter_N=4278199321&rating=all"
      ],
      "isRunning" : false,
      "isMostWantedList": true
    },
    {
      "id": "VM-22-0006",
      "marketplace": "Bol.com",
      "product": "8720254862699",
      "productId": "9300000053286204",
      "productTitle": "SmartphoneClip® Jeans grijs bandje geschikt voor Fitbit Luxe",
      "keywords": ["fitbit bandje", "fitbit luxe bandje", "fitbit luxe special edition", "fitbit luxe"],
      "keywordLink":
      [
        "https://www.bol.com/nl/nl/s/?page=1&searchtext=fitbit+bandje&view=list&filter_N=4278199321&12194=11-12&rating=all",
        "https://www.bol.com/nl/nl/s/?page=1&searchtext=fitbit+luxe+bandje&view=list&filter_N=4278199321&rating=all",
        "https://www.bol.com/nl/nl/s/?page=1&searchtext=fitbit+luxe&view=list&filter_N=4278199321&rating=all"
      ],
      "isRunning" : false,
      "isMostWantedList": true
    },
    {
      "id": "VM-22-0007",
      "marketplace": "Bol.com",
      "product": "8719325732030",
      "productId": "9200000121410629",
      "productTitle": "SmartphoneClip® Nylon Fitbit Bandje Zwart geschikt voor Fitbit Charge 3 / Charge 4",
      "keywords": ["fitbit bandje", "fitbit bandje charge 3", "fitbit charge 3 bandje", "fitbit bandje charge 4", "fitbit charge 4 bandje"],
      "keywordLink":
      [
        "https://www.bol.com/nl/nl/s/?page=1&searchtext=fitbit+bandje&view=list&filter_N=4278199321&12194=15-16&rating=all",
        "https://www.bol.com/nl/nl/s/?page=1&searchtext=fitbit+bandje+charge+3&view=list&filter_N=4278199321&rating=all",
        "https://www.bol.com/nl/nl/s/?page=1&searchtext=fitbit+charge+3+bandje&view=list&filter_N=4278199321&rating=all",
        "https://www.bol.com/nl/nl/s/?page=1&searchtext=fitbit+bandje+charge+4&view=list&filter_N=4278199321&rating=all",
        "https://www.bol.com/nl/nl/s/?page=1&searchtext=fitbit+charge+4+bandje&view=list&filter_N=4278199321&rating=all"
      ],
      "isRunning" : false,
      "isMostWantedList": true
    },
    {
      "id": "VM-22-0008",
      "marketplace": "Bol.com",
      "product": "8719992528288",
      "productId": "9200000108670948",
      "productTitle": "SmartphoneClip® Leer bruin Bandje classic geschikt voor Fitbit Charge 3 / Charge 4",
      "keywords": ["fitbit bandje", "fitbit charge 3 bandje", "fitbit charge 4 bandje", "fitbit bandje charge 3", "fitbit bandje charge 4"],
      "keywordLink":
      [
        "https://www.bol.com/nl/nl/s/?page=1&searchtext=fitbit+bandje&view=list&filter_N=4278199321&rating=all",
        "https://www.bol.com/nl/nl/s/?page=1&searchtext=fitbit+charge+3+bandje&view=list&filter_N=4278199321&rating=all",
        "https://www.bol.com/nl/nl/s/?page=1&searchtext=fitbit+charge+4+bandje&view=list&filter_N=4278199321&rating=all",
        "https://www.bol.com/nl/nl/s/?page=1&searchtext=fitbit+bandje+charge+3&view=list&filter_N=4278199321&rating=all",
        "https://www.bol.com/nl/nl/s/?page=1&searchtext=fitbit+bandje+charge+4&view=list&filter_N=4278199321&rating=all"
      ],
      "isRunning" : false,
      "isMostWantedList": true
    },
    {
      "id": "VM-22-0009",
      "marketplace": "Bol.com",
      "product": "8720254257365",
      "productId": "9300000014830481",
      "productTitle": "SmartphoneClip® Elastische leopard Bandje geschikt voor Fitbit Versa (1, 2, Lite)",
      "keywords": ["fitbit bandje versa", "fitbit bandje versa 2", "fitbit versa bandje", "fitbit bandje"],
      "keywordLink":
      [
        "https://www.bol.com/nl/nl/s/?page=1&searchtext=fitbit+bandje+versa&view=list&filter_N=4278199321&12194=11-12&rating=all",
        "https://www.bol.com/nl/nl/s/?page=1&searchtext=fitbit+bandje+versa+2&view=list&filter_N=4278199321&rating=all",
        "https://www.bol.com/nl/nl/s/?page=1&searchtext=fitbit+versa+bandje&view=list&filter_N=4278199321&rating=all",
        "https://www.bol.com/nl/nl/s/?page=1&searchtext=fitbit+bandje&view=list&filter_N=4278199321&rating=all"
      ],
      "isRunning" : false,
      "isMostWantedList": true
    },
    {
      "id": "VM-22-0010",
      "marketplace": "Bol.com",
      "product": "8720618313348",
      "productId": "9300000070638315",
      "productTitle": "SmartphoneClip® Leer Bruin Bandje Ibiza style geschikt voor Fitbit Charge 5",
      "keywords": ["fitbit bandje", "fitbit charge 5 bandje", "fitbit charge 6 bandje", "fitbit bandje charge 5"],
      "keywordLink":
      [
        "https://www.bol.com/nl/nl/s/?page=1&searchtext=fitbit+bandje&view=list&filter_N=4278199321&rating=all",
        "https://www.bol.com/nl/nl/s/?page=1&searchtext=fitbit+charge+5+bandje&view=list&filter_N=4278199321&rating=all",
        "https://www.bol.com/nl/nl/s/?page=1&searchtext=fitbit+charge+6+bandje&view=list&filter_N=4278199321&12194=19-20&rating=all",
        "https://www.bol.com/nl/nl/s/?page=1&searchtext=fitbit+bandje+charge+5&view=list&filter_N=4278199321&rating=all"
      ],
      "isRunning" : false,
      "isMostWantedList": true
    },
    {
      "id": "VM-22-0011",
      "marketplace": "Bol.com",
      "product": "7111603086087",
      "productId": "9200000094767705",
      "productTitle": "SmartphoneClip® Sport Bandje Black Silver Flowers Small - geschikt voor Fitbit Alta HR of Alta HR",
      "keywords": ["fitbit alta hr bandje", "fitbit alta bandje", "fitbit bandje"],
      "keywordLink":
      [
        "https://www.bol.com/nl/nl/s/?page=1&searchtext=fitbit+alta+hr+bandje&view=list&filter_N=4278199321&rating=all",
        "https://www.bol.com/nl/nl/s/?page=1&searchtext=fitbit+alta+bandje&view=list&filter_N=4278199321&rating=all",
        "https://www.bol.com/nl/nl/s/?page=1&searchtext=fitbit+bandje&view=list&filter_N=4278199321&12194=11-12&rating=all"
      ],
      "isRunning" : false,
      "isMostWantedList": true
    },
    {
      "id": "VM-22-0012",
      "marketplace": "Bol.com",
      "product": "7111606529970",
      "productId": "9200000094768664",
      "productTitle": "SmartphoneClip® Sport Bandje Leopard Small - geschikt voor Fitbit Flex 2",
      "keywords": ["fitbit bandje"],
      "keywordLink": ["https://www.bol.com/nl/nl/s/?page=1&searchtext=fitbit+bandje&view=list&filter_N=4278199321&12194=11-12&rating=all"],
      "isRunning" : false,
      "isMostWantedList": true
    },
    {
      "id": "VM-22-0013",
      "marketplace": "Bol.com",
      "product": "8720618313386",
      "productId": "9300000070639504",
      "productTitle": "SmartphoneClip® Leer klassiek zwart Grey Flower Bandje geschikt voor Fitbit Charge 5",
      "keywords": ["fitbit bandje", "fitbit charge 5 bandje", "fitbit charge 6 bandje", "fitbit bandje charge 5"],
      "keywordLink":
      [
        "https://www.bol.com/nl/nl/s/?page=1&searchtext=fitbit+bandje&view=list&filter_N=4278199321&12194=13-14&rating=all",
        "https://www.bol.com/nl/nl/s/?page=1&searchtext=fitbit+charge+5+bandje&view=list&filter_N=4278199321&rating=all",
        "https://www.bol.com/nl/nl/s/?page=1&searchtext=fitbit+bandje+charge+5&view=list&filter_N=4278199321&rating=all"
      ],
      "isRunning" : false,
      "isMostWantedList": true
    },
    {
      "id": "VM-22-0014",
      "marketplace": "Bol.com",
      "product": "8719992528479",
      "productId": "9200000110208975",
      "productTitle": "SmartphoneClip® Jeans Bandje Zwart Small geschikt voor Fitbit Inspire | Inspire 2 | Inspire HR",
      "keywords": ["fitbit bandje", "fitbit bandje inspire", "fitbit inspire 2 bandje"],
      "keywordLink":
      [
        "https://www.bol.com/nl/nl/s/?page=1&searchtext=fitbit+bandje&view=list&filter_N=4278199321&rating=all",
        "https://www.bol.com/nl/nl/s/?page=1&searchtext=fitbit+bandje+inspire&view=list&filter_N=4278199321&rating=all",
        "https://www.bol.com/nl/nl/s/?page=1&searchtext=fitbit+inspire+2+bandje&view=list&filter_N=4278199321&rating=all"
      ],
      "isRunning" : false,
      "isMostWantedList": true
    },
    {
      "id": "VM-22-0015",
      "marketplace": "Bol.com",
      "product": "8720618313379",
      "productId": "9300000070639502",
      "productTitle": "SmartphoneClip® Leer klassiek abrikoos Bandje geschikt voor Fitbit Charge 5 en 6",
      "keywords": ["fitbit bandje", "fitbit bandje charge 5", "fitbit charge 5 bandje", "fitbit charge 6 bandje"],
      "keywordLink":
      [
        "https://www.bol.com/nl/nl/s/?page=1&searchtext=fitbit+bandje&view=list&filter_N=4278199321&rating=all",
        "https://www.bol.com/nl/nl/s/?page=1&searchtext=fitbit+bandje+charge+5&view=list&filter_N=4278199321&rating=all",
        "https://www.bol.com/nl/nl/s/?page=1&searchtext=fitbit+charge+5+bandje&view=list&filter_N=4278199321&rating=all",
        "https://www.bol.com/nl/nl/s/?page=1&searchtext=fitbit+charge+6+bandje&view=list&filter_N=4278199321&rating=all"
      ],
      "isRunning" : false,
      "isMostWantedList": true
    },
    {
      "id": "VM-22-0016",
      "marketplace": "Bol.com",
      "product": "8719325643893",
      "productId": "9200000124366828",
      "productTitle": "SmartphoneClip® Bandje kalfsleer bruin Bandje geschikt voor Apple Watch Bandje 42, 44, 45, & 49mm (alle generaties)",
      "keywords": ["apple watch bandje", "bandje apple watch", "apple watch bandje 42 mm", "apple watch bandje 44 mm", "apple watch bandje 45 mm", "apple watch bandje 49 mm", "bandje apple watch 44 mm"],
      "keywordLink":
      [
        "https://www.bol.com/nl/nl/s/?page=1&searchtext=apple+watch+bandje&view=list&filter_N=4278199321&rating=all",
        "https://www.bol.com/nl/nl/s/?page=1&searchtext=bandje+apple+watch&view=list&filter_N=4278199321&rating=all",
        "https://www.bol.com/nl/nl/s/?page=1&searchtext=apple+watch+bandje+42+mm&view=list&filter_N=4278199321&rating=all",
        "https://www.bol.com/nl/nl/s/?page=1&searchtext=apple+watch+bandje+44+mm&view=list&filter_N=4278199321&rating=all",
        "https://www.bol.com/nl/nl/s/?page=1&searchtext=apple+watch+bandje+45+mm&view=list&filter_N=4278199321&rating=all",
        "https://www.bol.com/nl/nl/s/?page=1&searchtext=apple+watch+bandje+49+mm&view=list&filter_N=4278199321&rating=all",
        "https://www.bol.com/nl/nl/s/?page=1&searchtext=bandje+apple+watch+44+mm&view=list&filter_N=4278199321&rating=all"
      ],
      "isRunning" : false,
      "isMostWantedList": true
    },
    {
      "id": "VM-22-0017",
      "marketplace": "Bol.com",
      "product": "8720254862354",
      "productId": "9300000042089758",
      "productTitle": "SmartphoneClip® Metaal schakel zwart Bandje geschikt voor Apple Watch 42, 44, 45, & 49mm (alle generaties)",
      "keywords": ["apple watch bandje", "bandje apple watch", "apple watch bandje 42 mm", "apple watch bandje 44 mm", "apple watch bandje 45 mm", "apple watch bandje 49 mm", "bandje apple watch 44 mm"],
      "keywordLink":
      [
        "https://www.bol.com/nl/nl/s/?page=1&searchtext=apple+watch+bandje&view=list&filter_N=4278199321&rating=all",
        "https://www.bol.com/nl/nl/s/?page=1&searchtext=bandje+apple+watch&view=list&filter_N=4278199321&rating=all",
        "https://www.bol.com/nl/nl/s/?page=1&searchtext=apple+watch+bandje+42+mm&view=list&filter_N=4278199321&rating=all",
        "https://www.bol.com/nl/nl/s/?page=1&searchtext=apple+watch+bandje+44+mm&view=list&filter_N=4278199321&rating=all",
        "https://www.bol.com/nl/nl/s/?page=1&searchtext=apple+watch+bandje+45+mm&view=list&filter_N=4278199321&rating=all",
        "https://www.bol.com/nl/nl/s/?page=1&searchtext=apple+watch+bandje+49+mm&view=list&filter_N=4278199321&rating=all",
        "https://www.bol.com/nl/nl/s/?page=1&searchtext=bandje+apple+watch+44+mm&view=list&filter_N=4278199321&rating=all"
      ],
      "isRunning" : false,
      "isMostWantedList": true
    },
    {
      "id": "VM-22-0018",
      "marketplace": "Bol.com",
      "product": "8719992528189",
      "productId": "9200000108462051",
      "productTitle": "SmartphoneClip® Metaal double chain bandje zilver geschikt voor Apple Watch 38 en 40 mm",
      "keywords": ["apple watch bandje", "bandje apple watch", "apple watch bandje 38 mm", "apple watch bandje 40 mm", "apple watch bandje 41 mm", "bandje apple watch 40mm"],
      "keywordLink":
      [
        "https://www.bol.com/nl/nl/s/?page=1&searchtext=apple+watch+bandje&view=list&filter_N=4278199321&rating=all",
        "https://www.bol.com/nl/nl/s/?page=1&searchtext=bandje+apple+watch&view=list&filter_N=4278199321&rating=all",
        "https://www.bol.com/nl/nl/s/?page=1&searchtext=apple+watch+bandje+38+mm&view=list&filter_N=4278199321&rating=all",
        "https://www.bol.com/nl/nl/s/?page=1&searchtext=apple+watch+bandje+40+mm&view=list&filter_N=4278199321&rating=all"
      ],
      "isRunning" : false,
      "isMostWantedList": true
    },
    {
      "id": "VM-22-0019",
      "marketplace": "Bol.com",
      "product": "8720254257464",
      "productId": "9300000014830199",
      "productTitle": "SmartphoneClip® Elastische zwart zilver Bandje geschikt voor Apple Watch 38mm, 40mm en 41mm (alle generaties)",
      "keywords": ["apple watch bandje", "apple watch bandje 38 mm", "apple watch bandje 40 mm", "apple watch bandje 41 mm", "bandje apple watch", "bandje apple watch 40mm"],
      "keywordLink":
      [
        "https://www.bol.com/nl/nl/s/?page=1&searchtext=apple+watch+bandje&view=list&filter_N=4278199321&12194=11-12&rating=all",
        "https://www.bol.com/nl/nl/s/?page=1&searchtext=apple+watch+bandje+38+mm&view=list&filter_N=4278199321&rating=all",
        "https://www.bol.com/nl/nl/s/?page=1&searchtext=apple+watch+bandje+40+mm&view=list&filter_N=4278199321&rating=all",
        "https://www.bol.com/nl/nl/s/?page=1&searchtext=apple+watch+bandje+41+mm&view=list&filter_N=4278199321&rating=all",
        "https://www.bol.com/nl/nl/s/?page=1&searchtext=bandje+apple+watch&view=list&filter_N=4278199321&12194=11-12&rating=all",
        "https://www.bol.com/nl/nl/s/?page=1&searchtext=bandje+apple+watch+40mm&view=list&filter_N=4278199321&rating=all"
      ],
      "isRunning" : false,
      "isMostWantedList": true
    },
    {
      "id": "VM-22-0020",
      "marketplace": "Bol.com",
      "product": "8720618313867",
      "productId": "9300000105539654",
      "productTitle": "SmartphoneClip® Rugged Armor Iron Case Zwart met TPU band geschikt voor Apple Watch 45mm",
      "keywords": ["apple watch bandje", "apple watch bandje 45 mm", "bandje apple watch", "apple watch bandje 42 mm", "apple watch bandje 44 mm", "bandje apple watch 44 mm", "apple watch bandje 49 mm"],
      "keywordLink":
      [
        "https://www.bol.com/nl/nl/s/?page=1&searchtext=apple+watch+bandje&view=list&filter_N=4278199321&rating=all",
        "https://www.bol.com/nl/nl/s/?page=1&searchtext=apple+watch+bandje+45+mm&view=list&filter_N=4278199321&rating=all",
        "https://www.bol.com/nl/nl/s/?page=1&searchtext=bandje+apple+watch&view=list&filter_N=4278199321&rating=all"
      ],
      "isRunning" : false,
      "isMostWantedList": true
    },
    {
      "id": "VM-22-0021",
      "marketplace": "Bol.com",
      "product": "7110538663257",
      "productId": "9200000084907218",
      "productTitle": "SmartphoneClip® Leer Bruin Bandje Ibiza style geschikt voor Apple Watch 38mm, 40mm en 41mm (alle generaties)",
      "keywords": ["apple watch bandje", "apple watch bandje 40 mm", "bandje apple watch", "bandje apple watch 40mm", "apple watch bandje 41 mm", "apple watch bandje 38 mm"],
      "keywordLink":
      [
        "https://www.bol.com/nl/nl/s/?page=1&searchtext=apple+watch+bandje&view=list&filter_N=4278199321&rating=all",
        "https://www.bol.com/nl/nl/s/?page=1&searchtext=apple+watch+bandje+40+mm&view=list&filter_N=4278199321&rating=all",
        "https://www.bol.com/nl/nl/s/?page=1&searchtext=bandje+apple+watch&view=list&filter_N=4278199321&rating=all",
        "https://www.bol.com/nl/nl/s/?page=1&searchtext=bandje+apple+watch+40mm&view=list&filter_N=4278199321&rating=all",
        "https://www.bol.com/nl/nl/s/?page=1&searchtext=apple+watch+bandje+41+mm&view=list&filter_N=4278199321&rating=all",
        "https://www.bol.com/nl/nl/s/?page=1&searchtext=apple+watch+bandje+38+mm&view=list&filter_N=4278199321&rating=all"
      ],
      "isRunning" : false,
      "isMostWantedList": true
    },
    {
      "id": "VM-22-0022",
      "marketplace": "Bol.com",
      "product": "8719992214983",
      "productId": "9200000107804425",
      "productTitle": "SmartphoneClip® Leer zwart Bandje geschikt voor Apple Watch 38mm, 40mm en 41mm (alle generaties)",
      "keywords": ["apple watch bandje", "apple watch bandje 40 mm", "bandje apple watch", "bandje apple watch 40mm", "apple watch bandje 38 mm", "apple watch bandje 41 mm"],
      "keywordLink":
      [
        "https://www.bol.com/nl/nl/s/?page=1&searchtext=apple+watch+bandje&view=list&filter_N=4278199321&rating=all",
        "https://www.bol.com/nl/nl/s/?page=1&searchtext=apple+watch+bandje+40+mm&view=list&filter_N=4278199321&rating=all",
        "https://www.bol.com/nl/nl/s/?page=1&searchtext=bandje+apple+watch&view=list&filter_N=4278199321&rating=all",
        "https://www.bol.com/nl/nl/s/?page=1&searchtext=bandje+apple+watch+40mm&view=list&filter_N=4278199321&rating=all",
        "https://www.bol.com/nl/nl/s/?page=1&searchtext=apple+watch+bandje+38+mm&view=list&filter_N=4278199321&rating=all",
        "https://www.bol.com/nl/nl/s/?page=1&searchtext=apple+watch+bandje+41+mm&view=list&filter_N=4278199321&rating=all"
      ],
      "isRunning" : false,
      "isMostWantedList": true
    },
    {
      "id": "VM-22-0023",
      "marketplace": "Bol.com",
      "product": "8719325643909",
      "productId": "9200000124366867",
      "productTitle": "SmartphoneClip® Kalfsleer zwart Bandje geschikt voor Apple Watch 42-44-45-49mm (alle generaties)",
      "keywords": ["apple watch bandje", "apple watch bandje 44 mm", "apple watch bandje 45 mm", "bandje apple watch", "apple watch bandje 42 mm", "apple watch bandje 49 mm", "bandje apple watch 44 mm"],
      "keywordLink":
      [
        "https://www.bol.com/nl/nl/s/?page=1&searchtext=apple+watch+bandje&view=list&filter_N=4278199321&rating=all",
        "https://www.bol.com/nl/nl/s/?page=1&searchtext=apple+watch+bandje+44+mm&view=list&filter_N=4278199321&rating=all",
        "https://www.bol.com/nl/nl/s/?page=1&searchtext=apple+watch+bandje+45+mm&view=list&filter_N=4278199321&rating=all",
        "https://www.bol.com/nl/nl/s/?page=1&searchtext=bandje+apple+watch&view=list&filter_N=4278199321&rating=all",
        "https://www.bol.com/nl/nl/s/?page=1&searchtext=apple+watch+bandje+42+mm&view=list&filter_N=4278199321&rating=all",
        "https://www.bol.com/nl/nl/s/?page=1&searchtext=apple+watch+bandje+49+mm&view=list&filter_N=4278199321&rating=all",
        "https://www.bol.com/nl/nl/s/?page=1&searchtext=bandje+apple+watch+44+mm&view=list&filter_N=4278199321&rating=all"
      ],
      "isRunning" : false,
      "isMostWantedList": true
    },
    {
      "id": "VM-22-0024",
      "marketplace": "Bol.com",
      "product": "8720254257037",
      "productId": "9300000007823258",
      "productTitle": "SmartphoneClip® Leer zwart robuust Bandje geschikt voor Apple Watch 42mm, 44mm, 45mm, en 49 mm (alle generaties)",
      "keywords": ["apple watch bandje", "bandje apple watch", "apple watch bandje 42 mm", "apple watch bandje 44 mm", "bandje apple watch 44 mm", "apple watch bandje 45 mm", "apple watch bandje 49 mm"],
      "keywordLink":
      [
        "https://www.bol.com/nl/nl/s/?page=1&searchtext=apple+watch+bandje&view=list&filter_N=4278199321&12194=24-25&rating=all",
        "https://www.bol.com/nl/nl/s/?page=1&searchtext=bandje+apple+watch&view=list&filter_N=4278199321&12194=24-25&rating=all",
        "https://www.bol.com/nl/nl/s/?page=1&searchtext=apple+watch+bandje+42+mm&view=list&filter_N=4278199321&rating=all",
        "https://www.bol.com/nl/nl/s/?page=1&searchtext=apple+watch+bandje+44+mm&view=list&filter_N=4278199321&rating=all",
        "https://www.bol.com/nl/nl/s/?page=1&searchtext=bandje+apple+watch+44+mm&view=list&filter_N=4278199321&rating=all",
        "https://www.bol.com/nl/nl/s/?page=1&searchtext=apple+watch+bandje+45+mm&view=list&filter_N=4278199321&rating=all",
        "https://www.bol.com/nl/nl/s/?page=1&searchtext=apple+watch+bandje+49+mm&view=list&filter_N=4278199321&rating=all"
      ],
      "isRunning" : false,
      "isMostWantedList": true
    },
    {
      "id": "VM-22-0025",
      "marketplace": "Bol.com",
      "product": "8719325732085",
      "productId": "9200000125065968",
      "productTitle": "SmartphoneClip® Leer wax bruin Bandje geschikt voor Apple Watch 42mm, 44mm, 45mm, en 49 mm (alle generaties)",
      "keywords": ["apple watch bandje", "apple watch bandje 45 mm", "bandje apple watch", "apple watch bandje 42 mm", "apple watch bandje 44 mm", "bandje apple watch 44 mm", "apple watch bandje 49 mm"],
      "keywordLink":
      [
        "https://www.bol.com/nl/nl/s/?page=1&searchtext=apple+watch+bandje&view=list&filter_N=4278199321&rating=all",
        "https://www.bol.com/nl/nl/s/?page=1&searchtext=apple+watch+bandje+45+mm&view=list&filter_N=4278199321&rating=all",
        "https://www.bol.com/nl/nl/s/?page=1&searchtext=bandje+apple+watch&view=list&filter_N=4278199321&rating=all",
        "https://www.bol.com/nl/nl/s/?page=1&searchtext=apple+watch+bandje+42+mm&view=list&filter_N=4278199321&rating=all",
        "https://www.bol.com/nl/nl/s/?page=1&searchtext=apple+watch+bandje+44+mm&view=list&filter_N=4278199321&rating=all",
        "https://www.bol.com/nl/nl/s/?page=1&searchtext=bandje+apple+watch+44+mm&view=list&filter_N=4278199321&rating=all",
        "https://www.bol.com/nl/nl/s/?page=1&searchtext=apple+watch+bandje+49+mm&view=list&filter_N=4278199321&rating=all"
      ],
      "isRunning" : false,
      "isMostWantedList": true
    },
    {
      "id": "VM-22-0026",
      "marketplace": "Bol.com",
      "product": "8719992528196",
      "productId": "9200000108462047",
      "productTitle": "SmartphoneClip® Metaal double chain zilver Bandje geschikt voor Apple Watch 42mm, 44mm, 45mm, en 49 mm (alle generaties)",
      "keywords": ["apple watch bandje", "apple watch bandje 45 mm", "bandje apple watch", "apple watch bandje 42 mm", "apple watch bandje 44 mm", "bandje apple watch 44 mm", "apple watch bandje 49 mm"],
      "keywordLink":
      [
        "https://www.bol.com/nl/nl/s/?page=1&searchtext=apple+watch+bandje&view=list&filter_N=4278199321&rating=all",
        "https://www.bol.com/nl/nl/s/?page=1&searchtext=apple+watch+bandje+45+mm&view=list&filter_N=4278199321&rating=all",
        "https://www.bol.com/nl/nl/s/?page=1&searchtext=bandje+apple+watch&view=list&filter_N=4278199321&rating=all",
        "https://www.bol.com/nl/nl/s/?page=1&searchtext=apple+watch+bandje+42+mm&view=list&filter_N=4278199321&rating=all",
        "https://www.bol.com/nl/nl/s/?page=1&searchtext=apple+watch+bandje+44+mm&view=list&filter_N=4278199321&rating=all",
        "https://www.bol.com/nl/nl/s/?page=1&searchtext=bandje+apple+watch+44+mm&view=list&filter_N=4278199321&rating=all",
        "https://www.bol.com/nl/nl/s/?page=1&searchtext=apple+watch+bandje+49+mm&view=list&filter_N=4278199321&rating=all"
      ],
      "isRunning" : false,
      "isMostWantedList": true
    },
    {
      "id": "VM-22-0027",
      "marketplace": "Bol.com",
      "product": "8720254862064",
      "productId": "9300000034958807",
      "productTitle": "SmartphoneClip® Leer/Siliconen Bandje zwart geschikt voor Apple Watch 42mm, 44mm, 45mm, en 49 mm (alle generaties)",
      "keywords": ["apple watch bandje", "apple watch bandje 45 mm", "bandje apple watch", "apple watch bandje 42 mm", "apple watch bandje 44 mm", "bandje apple watch 44 mm", "apple watch bandje 49 mm"],
      "keywordLink":
      [
        "https://www.bol.com/nl/nl/s/?page=1&searchtext=apple+watch+bandje&view=list&filter_N=4278199321&12194=22-23&rating=all",
        "https://www.bol.com/nl/nl/s/?page=1&searchtext=apple+watch+bandje+45+mm&view=list&filter_N=4278199321&rating=all",
        "https://www.bol.com/nl/nl/s/?page=1&searchtext=bandje+apple+watch&view=list&filter_N=4278199321&12194=22-23&rating=all",
        "https://www.bol.com/nl/nl/s/?page=1&searchtext=apple+watch+bandje+42+mm&view=list&filter_N=4278199321&rating=all",
        "https://www.bol.com/nl/nl/s/?page=1&searchtext=apple+watch+bandje+44+mm&view=list&filter_N=4278199321&rating=all",
        "https://www.bol.com/nl/nl/s/?page=1&searchtext=bandje+apple+watch+44+mm&view=list&filter_N=4278199321&rating=all",
        "https://www.bol.com/nl/nl/s/?page=1&searchtext=apple+watch+bandje+49+mm&view=list&filter_N=4278199321&rating=all"
      ],
      "isRunning" : false,
      "isMostWantedList": true
    },
    {
      "id": "VM-22-0028",
      "marketplace": "Bol.com",
      "product": "8719992214464",
      "productId": "9200000100526500",
      "productTitle": "SmartphoneClip® Bandje leer glitter zilver geschikt voor Apple Watch 38mm-40mm series 1,2,3,4 en 5 - Apple watch bandje",
      "keywords": ["apple watch bandje", "apple watch bandje 40 mm", "apple watch bandje 41 mm", "apple watch bandje 38 mm", "bandje apple watch", "fitbit charge 4 bandje"],
      "keywordLink":
      [
        "https://www.bol.com/nl/nl/s/?page=1&searchtext=apple+watch+bandje&view=list&filter_N=4278199321&rating=all",
        "https://www.bol.com/nl/nl/s/?page=1&searchtext=apple+watch+bandje+40+mm&view=list&filter_N=4278199321&rating=all",
        "https://www.bol.com/nl/nl/s/?page=1&searchtext=apple+watch+bandje+41+mm&view=list&filter_N=4278199321&12194=10-11&rating=all",
        "https://www.bol.com/nl/nl/s/?page=1&searchtext=apple+watch+bandje+38+mm&view=list&filter_N=4278199321&rating=all",
        "https://www.bol.com/nl/nl/s/?page=1&searchtext=bandje+apple+watch&view=list&filter_N=4278199321&rating=all",
        ""
      ],
      "isRunning" : false,
      "isMostWantedList": true
    },
    {
      "id": "VM-22-0029",
      "marketplace": "Bol.com",
      "product": "7110533587626",
      "productId": "9200000084907292",
      "productTitle": "SmartphoneClip® Leer Zwart Bandje Ibiza style geschikt voor Apple Watch 42mm, 44mm, 45mm, en 49 mm (alle generaties)",
      "keywords": ["apple watch bandje 44 mm", "bandje apple watch", "bandje apple watch 44 mm", "apple watch bandje 49 mm", "apple watch bandje", "apple watch bandje", "apple watch bandje 42 mm"],
      "keywordLink":
      [
        "https://www.bol.com/nl/nl/s/?page=1&searchtext=apple+watch+bandje+44+mm&view=list&filter_N=4278199321&rating=all",
        "https://www.bol.com/nl/nl/s/?page=1&searchtext=bandje+apple+watch&view=list&filter_N=4278199321&rating=all",
        "https://www.bol.com/nl/nl/s/?page=1&searchtext=bandje+apple+watch+44+mm&view=list&filter_N=4278199321&rating=all",
        "https://www.bol.com/nl/nl/s/?page=1&searchtext=apple+watch+bandje+49+mm&view=list&filter_N=4278199321&rating=all",
        "https://www.bol.com/nl/nl/s/?page=1&searchtext=apple+watch+bandje&view=list&filter_N=4278199321&rating=all",
        "https://www.bol.com/nl/nl/s/?page=1&searchtext=apple+watch+bandje+42+mm&view=list&filter_N=4278199321&rating=all",
        "https://www.bol.com/nl/nl/s/?page=1&searchtext=apple+watch+bandje+45+mm&view=list&filter_N=4278199321&rating=all"
      ],
      "isRunning" : false,
      "isMostWantedList": true
    },
    {
      "id": "VM-22-0030",
      "marketplace": "Bol.com",
      "product": "8720254257020",
      "productId": "9300000007823253",
      "productTitle": "SmartphoneClip® Leer bruin met schroef Bandje geschikt voor Apple Watch 42mm, 44mm, 45mm, en 49 mm (alle generaties)",
      "keywords": ["apple watch bandje 44 mm", "bandje apple watch", "bandje apple watch 44 mm", "apple watch bandje", "apple watch bandje 42 mm", "apple watch bandje 45 mm", "apple watch bandje 49 mm"],
      "keywordLink":
      [
        "https://www.bol.com/nl/nl/s/?page=1&searchtext=apple+watch+bandje+44+mm&view=list&filter_N=4278199321&rating=all",
        "https://www.bol.com/nl/nl/s/?page=1&searchtext=bandje+apple+watch&view=list&filter_N=4278199321&rating=all",
        "https://www.bol.com/nl/nl/s/?page=1&searchtext=bandje+apple+watch+44+mm&view=list&filter_N=4278199321&rating=all",
        "https://www.bol.com/nl/nl/s/?page=1&searchtext=apple+watch+bandje&view=list&filter_N=4278199321&rating=all",
        "https://www.bol.com/nl/nl/s/?page=1&searchtext=apple+watch+bandje+42+mm&view=list&filter_N=4278199321&rating=all",
        "https://www.bol.com/nl/nl/s/?page=1&searchtext=apple+watch+bandje+45+mm&view=list&filter_N=4278199321&rating=all",
        "https://www.bol.com/nl/nl/s/?page=1&searchtext=apple+watch+bandje+49+mm&view=list&filter_N=4278199321&rating=all"
      ],
      "isRunning" : false,
      "isMostWantedList": true
    }
  ]
}